tfparse.cpython-310-darwin.so
tfparse.cpython-310-darwin.h
tfparse-0.6.19.dist-info/RECORD
tfparse-0.6.19.dist-info/WHEEL
tfparse-0.6.19.dist-info/top_level.txt
tfparse-0.6.19.dist-info/METADATA
tfparse-0.6.19.dist-info/licenses/LICENSE
tfparse/_tfparse.py
tfparse/__init__.py
tfparse/build_cffi.py
