Metadata-Version: 2.4
Name: tfparse
Version: 0.6.19
Summary: Python HCL/Terraform parser via extension for AquaSecurity defsec
Home-page: https://github.com/cloud-custodian/tfparse
Author: Wayne Witzel III
Author-email: wayne@stacklet.io
Maintainer: Cloud Custodian Project
Maintainer-email: cloud-custodian@googlegroups.com
License: Apache-2.0
Classifier: Development Status :: 4 - Beta
Classifier: Intended Audience :: Developers
Classifier: Programming Language :: Python :: 3.10
Classifier: Programming Language :: Python :: 3.11
Classifier: Programming Language :: Python :: 3.12
Classifier: Programming Language :: Python :: 3.13
Classifier: Programming Language :: Python :: 3.14
License-File: LICENSE
Requires-Dist: cffi>=1.0.0
Dynamic: author
Dynamic: author-email
Dynamic: classifier
Dynamic: description
Dynamic: description-content-type
Dynamic: home-page
Dynamic: license
Dynamic: license-file
Dynamic: maintainer
Dynamic: maintainer-email
Dynamic: requires-dist
Dynamic: summary
